{"name":"raiseissue","description":"raise issue","indexes":[],"schemaDef":[{"name":"description","type":"string","isRequired":false,"isEncrypted":false,"reference":{},"maxLength":"","default":""},{"name":"issueType","type":"string","isRequired":false,"isEncrypted":false,"reference":{},"maxLength":"","default":""},{"name":"sys_Id","type":"string","isRequired":true,"readOnly":true},{"name":"Created_On","type":"date","isRequired":true,"readOnly":true},{"name":"Updated_On","type":"date","isRequired":true,"readOnly":true},{"name":"Created_By","type":"string","isRequired":true,"readOnly":true},{"name":"Updated_By","type":"string","isRequired":true,"readOnly":true}]}